am4894dev/__init__.py
am4894dev/dev.py
am4894dev/netdata/__init__.py
am4894dev/netdata/api.py
am4894dev-0.4.2.dist-info/AUTHORS.rst
am4894dev-0.4.2.dist-info/LICENSE
am4894dev-0.4.2.dist-info/METADATA
am4894dev-0.4.2.dist-info/WHEEL
am4894dev-0.4.2.dist-info/top_level.txt
am4894dev-0.4.2.dist-info/RECORD
