Metadata-Version: 2.1
Name: am4894dev
Version: 0.4.2
Summary: My dev package for playing around with.
Home-page: https://github.com/andrewm4894/am4894dev
Author: Andrew Maguire
Author-email: andrewm4894@gmail.com
License: MIT license
Keywords: am4894dev
Platform: UNKNOWN
Classifier: Development Status :: 2 - Pre-Alpha
Classifier: Intended Audience :: Developers
Classifier: License :: OSI Approved :: MIT License
Classifier: Natural Language :: English
Classifier: Programming Language :: Python :: 3.6
Classifier: Programming Language :: Python :: 3.7
Classifier: Programming Language :: Python :: 3.8
Requires-Python: >=3.6
